Kalman.py
__init__.py
cov_to_inf.py
evidence.py
id_predict.py
inf_to_cov.py
mupdate.py
removal.py
reversal.py
tupdate.py
pykalmanfilter-1.1.1.dist-info/licenses/LICENSE
pykalmanfilter-1.1.1.dist-info/METADATA
pykalmanfilter-1.1.1.dist-info/WHEEL
pykalmanfilter-1.1.1.dist-info/top_level.txt
pykalmanfilter-1.1.1.dist-info/RECORD
